zonis/__init__.py
zonis/client.py
zonis/exceptions.py
zonis/packet.py
zonis/route_registration.py
zonis/router.py
zonis/server.py
zonis/util.py
zonis/ws_impls.py
zonis-2.1.0.dist-info/LICENSE
zonis-2.1.0.dist-info/METADATA
zonis-2.1.0.dist-info/WHEEL
zonis-2.1.0.dist-info/RECORD
