Metadata-Version: 2.1
Name: zonis
Version: 2.1.0
Summary: Agnostic IPC for Python programs 
Author: skelmis
Author-email: skelmis.craft@gmail.com
Requires-Python: >=3.10,<4.0
Classifier: Programming Language :: Python :: 3
Classifier: Programming Language :: Python :: 3.10
Classifier: Programming Language :: Python :: 3.11
Classifier: Programming Language :: Python :: 3.12
Requires-Dist: websockets (>=10.4,<11.0)
